stravaheatmap/__init__.py
stravaheatmap/cartograph/__init__.py
stravaheatmap/cartograph/__main__.py
stravaheatmap/cartograph/onlinemap.py
stravaheatmap/josm/__init__.py
stravaheatmap/josm/__main__.py
stravaheatmap/josm/imgupdater.py
stravaheatmap-4.3.dist-info/LICENSE
stravaheatmap-4.3.dist-info/METADATA
stravaheatmap-4.3.dist-info/WHEEL
stravaheatmap-4.3.dist-info/top_level.txt
stravaheatmap-4.3.dist-info/RECORD
