Metadata-Version: 2.1
Name: stravaheatmap
Version: 4.3
Summary: A python utility to provide the high resolution Strava Heatmap to cartographic applications like JOSM and Cartograph Maps.
Home-page: https://github.com/solitone/stravaheatmap
Author: solitone
Author-email: solitone@mail.com
Project-URL: Bug Tracker, https://github.com/solitone/stravaheatmap/issues
Classifier: Programming Language :: Python :: 3
Classifier: License :: OSI Approved :: GNU General Public License v3 (GPLv3)
Classifier: Operating System :: OS Independent
Requires-Python: >=3.6
License-File: LICENSE
Requires-Dist: colorama
Requires-Dist: stravacookies
